d_clean/__init__.py
d_clean/cli.py
d_clean/common.py
d_clean/tasks.py
d_clean-0.0.8.dist-info/DESCRIPTION.rst
d_clean-0.0.8.dist-info/METADATA
d_clean-0.0.8.dist-info/RECORD
d_clean-0.0.8.dist-info/WHEEL
d_clean-0.0.8.dist-info/entry_points.txt
d_clean-0.0.8.dist-info/metadata.json
d_clean-0.0.8.dist-info/top_level.txt
